ghcTestPkg/__init__.py
ghcTestPkg/ghcTestPkg.py
ghcTestPkg-0.1.5.dist-info/LICENSE
ghcTestPkg-0.1.5.dist-info/METADATA
ghcTestPkg-0.1.5.dist-info/WHEEL
ghcTestPkg-0.1.5.dist-info/top_level.txt
ghcTestPkg-0.1.5.dist-info/RECORD
